{"id":"preferences.keymap","name":"|b|messages.KeyMapBundle|k|keymap.display.name|","entries":[{"hit":"|b|messages.LearnBundle|k|action.NextLessonAction.text|","path":"ActionManager"},{"hit":"|b|messages.LearnBundle|k|action.PreviousLessonAction.text|","path":"ActionManager"},{"hit":"|b|messages.LearnBundle|k|action.ResetLearningProgressAction.text|","path":"ActionManager"},{"hit":"|b|messages.LearnBundle|k|action.RestartLessonAction.text|","path":"ActionManager"},{"hit":"|b|messages.LearnBundle|k|action.ShowLearnPanel.text|","path":"ActionManager"}]}
{"id":"FeaturesTrainerSettingsPanel","name":"|b|messages.LearnBundle|k|learn.options.panel.name|","entries":[{"hit":"Java"},{"hit":"Kotlin"},{"hit":"|b|messages.LearnBundle|k|learn.option.main.language|"},{"hit":"|b|messages.LearnBundle|k|learn.option.reset.progress|"},{"hit":"|b|messages.LearnBundle|k|learn.options.panel.name|"},{"hit":"|b|messages.LearnBundle|k|settings.checkbox.show.notifications.new.lessons|"}]}
{"id":"org.intellij.featuresSuggester.FeatureSuggesterConfigurable","name":"|b|messages.FeatureSuggesterBundle|k|configurable.name|","entries":[{"hit":"|b|messages.FeatureSuggesterBundle|k|completion.popup.name|"},{"hit":"|b|messages.FeatureSuggesterBundle|k|configurable.name|"},{"hit":"|b|messages.FeatureSuggesterBundle|k|configurable.show.suggestions.checkbox|"},{"hit":"|b|messages.FeatureSuggesterBundle|k|edit.breakpoint.name|"},{"hit":"|b|messages.FeatureSuggesterBundle|k|file.structure.name|"},{"hit":"|b|messages.FeatureSuggesterBundle|k|introduce.variable.name|"},{"hit":"|b|messages.FeatureSuggesterBundle|k|line.commenting.name|"},{"hit":"|b|messages.FeatureSuggesterBundle|k|mute.breakpoints.name|"},{"hit":"|b|messages.FeatureSuggesterBundle|k|paste.from.history.name|"},{"hit":"|b|messages.FeatureSuggesterBundle|k|quick.evaluate.name|"},{"hit":"|b|messages.FeatureSuggesterBundle|k|replace.completion.name|"},{"hit":"|b|messages.FeatureSuggesterBundle|k|run.to.cursor.name|"},{"hit":"|b|messages.FeatureSuggesterBundle|k|surround.with.name|"},{"hit":"|b|messages.FeatureSuggesterBundle|k|unwrap.name|"}]}
